podcastpy/__init__.py
podcastpy/cmd.py
podcastpy/ffmpeg.py
podcastpy/podcastpy.py
podcastpy/version.py
podcastpy-0.0.4.dist-info/LICENSE
podcastpy-0.0.4.dist-info/METADATA
podcastpy-0.0.4.dist-info/WHEEL
podcastpy-0.0.4.dist-info/top_level.txt
podcastpy-0.0.4.dist-info/RECORD
