Metadata-Version: 2.1
Name: podcastpy
Version: 0.0.4
Summary: PodcastPy - Python Tools for Podcast
Home-page: https://github.com/eiproject/PodcastPy
Author: M Razif Rizqullah
Author-email: razifrizqullah@gmail.com
License: MIT
Keywords: python,glrlm,feature extraction,image processing
Platform: UNKNOWN
Classifier: Development Status :: 5 - Production/Stable
Classifier: Intended Audience :: Developers
Classifier: Programming Language :: Python :: 3
Classifier: Programming Language :: Python :: 3.8
Classifier: Operating System :: Unix
Classifier: Operating System :: MacOS :: MacOS X
Classifier: Operating System :: Microsoft :: Windows
License-File: LICENSE
Requires-Dist: tqdm
Requires-Dist: numpy
Requires-Dist: scipy
Requires-Dist: matplotlib
Requires-Dist: pydub
